pyshell_msg/__init__.py
pyshell_msg/shell.py
pyshell_msg-0.1.1.dist-info/METADATA
pyshell_msg-0.1.1.dist-info/WHEEL
pyshell_msg-0.1.1.dist-info/top_level.txt
pyshell_msg-0.1.1.dist-info/RECORD
